rulz/__init__.py
rulz/dr.py
rulz/loader.py
rulz/plugins/__init__.py
rulz/plugins/demo.py
rulz/tests/__init__.py
rulz/tests/test_dependencies.py
rulz-0.0.5.dist-info/LICENSE
rulz-0.0.5.dist-info/METADATA
rulz-0.0.5.dist-info/WHEEL
rulz-0.0.5.dist-info/top_level.txt
rulz-0.0.5.dist-info/RECORD
