Metadata-Version: 2.1
Name: rulz
Version: 0.0.5
Summary: rulz is a decorator based IoC framework.
Home-page: https://github.com/csams/rulz
Author: Christopher W. Sams
License: Apache 2.0
Platform: UNKNOWN
Classifier: Intended Audience :: Developers
Classifier: Natural Language :: English
Classifier: License :: OSI Approved :: Apache Software License
Classifier: Programming Language :: Python
Classifier: Programming Language :: Python :: 3.6
Classifier: Programming Language :: Python :: 3.7
Provides-Extra: develop
Requires-Dist: flake8 ; extra == 'develop'
Requires-Dist: setuptools ; extra == 'develop'
Requires-Dist: ipython ; extra == 'develop'
Requires-Dist: pytest ; extra == 'develop'
Requires-Dist: wheel ; extra == 'develop'
Requires-Dist: twine ; extra == 'develop'
